Metadata-Version: 1.0
Name: array-to-struct
Version: 1.0
Summary: Able to make flat array from nested structure and back
Home-page: https://github.com/BalanDmitriy/Project_BalanDmitry_IVT3-20.git
Author: DmitryBalan
Author-email: b4landmitry@yandex.ru
License: UNKNOWN
Platform: UNKNOWN
